RESTApiGen.py
RESTApiGen-0.2.0.1.dist-info/LICENSE
RESTApiGen-0.2.0.1.dist-info/METADATA
RESTApiGen-0.2.0.1.dist-info/WHEEL
RESTApiGen-0.2.0.1.dist-info/entry_points.txt
RESTApiGen-0.2.0.1.dist-info/top_level.txt
RESTApiGen-0.2.0.1.dist-info/RECORD
