Metadata-Version: 2.1
Name: RESTApiGen
Version: 0.2.0.1
Summary: REST API auto-generator.
Home-page: https://github.com/Saiyam-J/RESTApiGen
Author: Saiyam Jain
License: MIT
Requires-Python: >=3.10
License-File: LICENSE
Requires-Dist: pymysql (>=1.0.2)
Requires-Dist: inflect
Requires-Dist: flask
Requires-Dist: flask-sqlalchemy
Requires-Dist: flask-restful
Requires-Dist: flask-blueprint
Requires-Dist: flask-marshmallow
Requires-Dist: marshmallow-sqlalchemy
Requires-Dist: cryptography
